[
    {
        "cid": "UgzDKS1ZujO7_jrZqaR4AaABAg",
        "text": "Thanks abel!  Helpful info new share yareken",
        "time": "4 years ago",
        "author": "@dybrilliantsketches5694",
        "channel": "UCC_cYdMbZTrWKd-uYBwCMkQ",
        "votes": "28",
        "replies": "",
        "photo": "https://yt3.ggpht.com/MDpyaBUohvRL7R6cLmYB8hDKmY1AqSuVeM5eBgePQoanVEv0uK_WTSioH0i5Lyr8nXHLuiwINSw=s88-c-k-c0x00ffffff-no-rj",
        "heart": true,
        "reply": false,
        "time_parsed": 1623051336.699321
    },
    {
        "cid": "UgzG1K3pT8pqCyr9LiR4AaABAg",
        "text": "ሰለም  አቤሉ ኡንከን በሰለም ማጠህ",
        "time": "4 years ago",
        "author": "@neimayassin1145",
        "channel": "UCADVypL3pSJqwiOcCMelzWg",
        "votes": "3",
        "replies": "",
        "photo": "https://yt3.ggpht.com/KVNRRaUQd1zpGulZlDb1LhppuB695WPop3IO12bgmD3zXbZcw2eV2Tw7yuONBf0836zk9z9V0Q=s88-c-k-c0x00ffffff-no-rj",
        "heart": true,
        "reply": false,
        "time_parsed": 1623051336.701682
    },
    {
        "cid": "Ugx61Hgw0j40vi2WOWt4AaABAg",
        "text": "አቤሎ እንኳን ደህና መጣህ ምርጥ ምርጥ መረጃዎ ስለምትሰጠን ከልብ እናመሠግናለን🙏🙏👌",
        "time": "4 years ago",
        "author": "@denbena3718",
        "channel": "UC5xhuVz6yuf28Ume5TlnTGA",
        "votes": "4",
        "replies": "",
        "photo": "https://yt3.ggpht.com/PSN7EYF2YIrs755IshlkrPIm9TJt51nh25_UQjIWzxzgFNIG8SQKwl9yZ1scmzVVp-o0SRnCTA=s88-c-k-c0x00ffffff-no-rj",
        "heart": true,
        "reply": false,
        "time_parsed": 1623051336.704772
    },
    {
        "cid": "UgzPo2jmIN4Cw_a4PAh4AaABAg",
        "text": "Abelo.lemesexen.mereja.ulu.enamesegenalem.berta🙏🙏🙏🙏🙏🙏🙏🙏🙏🙏🙏🙏🙏",
        "time": "4 years ago",
        "author": "@بناتجريليك",
        "channel": "UC7-03JyIwrz_5eNvkUP6klA",
        "votes": "2",
        "replies": "",
        "photo": "https://yt3.ggpht.com/ytc/AIdro_kqoX-TlIGshsOE79DDuAMVddihJZEXdyvcRrcLXYg=s88-c-k-c0x00ffffff-no-rj",
        "heart": true,
        "reply": false,
        "time_parsed": 1623051336.707091
    },
    {
        "cid": "Ugyz3sTxxI6-YSS_ZjV4AaABAg",
        "text": "እናመሰግናለን አቤል",
        "time": "4 years ago",
        "author": "@ጽዮንጽዮን-ሸ5ኀ",
        "channel": "UCY9IDB5HWfNjaohDHd_eBlA",
        "votes": "1",
        "replies": "",
        "photo": "https://yt3.ggpht.com/YSba9BODFUr5xJfG4S_XsApZOmIyiYmDg-aU5wjXxmkasZ_GKptpRhkIq2_ARufltuVlFXQgYbc=s88-c-k-c0x00ffffff-no-rj",
        "heart": true,
        "reply": false,
        "time_parsed": 1623051336.709797
    },
    {
        "cid": "UgziPx48R6ju48laT3d4AaABAg",
        "text": "የማርከን አባት እንኳን በደና መጣክ  መልካም ምርጥ ሰው አቤል  ጥሩ መረጃ ነው",
        "time": "4 years ago",
        "author": "@hosanna3393",
        "channel": "UCwEddvi2m4aiM0blrFi2O0A",
        "votes": "3",
        "replies": "",
        "photo": "https://yt3.ggpht.com/7f455q8x2-i4XaXG36pOqGYyFsm9L7OfdLl_tzz2cdUIAiF-kucxPHiJ5-j7zvUJ2bhJ2k3Law=s88-c-k-c0x00ffffff-no-rj",
        "heart": true,
        "reply": false,
        "time_parsed": 1623051336.71213
    },
    {
        "cid": "UgyGXW2Oe3ZWLR7DhwV4AaABAg",
        "text": "እኔ የሰው ቪዲዮ አልጠቀምም እናመሰግናለን አቤል",
        "time": "4 years ago (edited)",
        "author": "@aishatube2939",
        "channel": "UCzaQVcTsI-_rxoAF4eYMtWA",
        "votes": "2",
        "replies": "",
        "photo": "https://yt3.ggpht.com/ytc/AIdro_kkdpIzNVha5gWzzyKZpo7y-7JTxGB5FoDm0y-bkFUgvQ=s88-c-k-c0x00ffffff-no-rj",
        "heart": true,
        "reply": false,
        "time_parsed": 1623051336.714689
    },
    {
        "cid": "UgwAeX0IHO-CQL14MFh4AaABAg",
        "text": "አቤሎ ማርያም በጣም ቀና ሰው ነህ እናመሰግናለን  ተባረክልን🙏🏿⛪",
        "time": "1 year ago",
        "author": "@hareggenene",
        "channel": "UCPsu31wGk5nmJ4L3_gdBXRw",
        "votes": "0",
        "replies": "",
        "photo": "https://yt3.ggpht.com/4YqsnMi9X5TiR4Jbi-rD4v-ZnqFW4gJcay7i6eZ08DZKQttAq374Xtag_2ki4Xs7_O5uzHZ6=s88-c-k-c0x00ffffff-no-rj",
        "heart": false,
        "reply": false,
        "time_parsed": 1717745736.717191
    },
    {
        "cid": "Ugx9uJChj2vLUMUsVPh4AaABAg",
        "text": "ሰማ እንደ ምወድህ ግን ታቃለህ በርታ",
        "time": "4 years ago",
        "author": "@akmelbest9145",
        "channel": "UCZjxyBn3DiTkPQIJ0TZne3g",
        "votes": "1",
        "replies": "",
        "photo": "https://yt3.ggpht.com/ytc/AIdro_k6yrJUHQENy6CU3nPYbHnTp_Zk-KVTy5570JbB8QY=s88-c-k-c0x00ffffff-no-rj",
        "heart": true,
        "reply": false,
        "time_parsed": 1623051336.719435
    },
    {
        "cid": "Ugxypj1q7LcAl09ZaVd4AaABAg",
        "text": "እናመሰግናለን",
        "time": "7 months ago",
        "author": "@DagInfo-s1k",
        "channel": "UCF_9W71T2VJD65SjiK90GJQ",
        "votes": "1",
        "replies": "",
        "photo": "https://yt3.ggpht.com/MuXNlOpJ3o3IwSBZUPCJWy-N_PKB5SHcMjGNZyIKpZclcf4ElIlqSuwG-6xcu7XVochyG78m=s88-c-k-c0x00ffffff-no-rj",
        "heart": false,
        "reply": false,
        "time_parsed": 1730964936.722756
    },
    {
        "cid": "UgxTZedM0XYaEMcxF294AaABAg",
        "text": "Thanks for share your idea",
        "time": "2 years ago",
        "author": "@jemaritube",
        "channel": "UCbDCd91Sj5iEzT08eC7QSuA",
        "votes": "1",
        "replies": "",
        "photo": "https://yt3.ggpht.com/D26dCLLoxxff-BDX9lS6Wsq2h4O4YVAWp19hk-wmObthPDjd3brMayvUdJpRcbPxr1aO-4aj=s88-c-k-c0x00ffffff-no-rj",
        "heart": false,
        "reply": false,
        "time_parsed": 1686123336.725308
    },
    {
        "cid": "UgyBcM6PuRG3grL40Ot4AaABAg",
        "text": "ሥለ creative commons ትንሽ ብትጨምርበት ደሥ ይለኝ ነበር። all the time wish you \"all the best ABELO\"",
        "time": "4 years ago",
        "author": "@petrosetube624",
        "channel": "UC38L4D-fc90m5YQxse26CrQ",
        "votes": "5",
        "replies": "",
        "photo": "https://yt3.ggpht.com/0rb4DGJQGsStKVIoIt_Spcvykqp3n1Jnw9VD-63fsSt7UQEclacdpfad8fL40w0AKlJhi7o4vgg=s88-c-k-c0x00ffffff-no-rj",
        "heart": true,
        "reply": false,
        "time_parsed": 1623051336.727562
    },
    {
        "cid": "UgzhqHyQce3QG511VJN4AaABAg",
        "text": "enamesegenalen abelaye....btamm tekami mereja nw",
        "time": "4 years ago",
        "author": "@ZemranGirma",
        "channel": "UCWiVaxLHH_8WiOnEDE7ig2w",
        "votes": "3",
        "replies": "",
        "photo": "https://yt3.ggpht.com/ytc/AIdro_la-Nmhmwo5sLmWm4B83Ewah1gflhuVIz6V5vzxW6RCqHo=s88-c-k-c0x00ffffff-no-rj",
        "heart": true,
        "reply": false,
        "time_parsed": 1623051336.729751
    },
    {
        "cid": "Ugzj8TDOL2dwTeXH0lZ4AaABAg",
        "text": "አንደኛ በርታ እዳት ይምከታተለው  የለም",
        "time": "4 years ago (edited)",
        "author": "@sitinamohammed8032",
        "channel": "UCW67oNUKSAKrwUX6zq1d3NQ",
        "votes": "3",
        "replies": "",
        "photo": "https://yt3.ggpht.com/ytc/AIdro_kDJO3HFNigvCIJHm4RiFH6o7jnbK7moItRWy-n1rdNRW0=s88-c-k-c0x00ffffff-no-rj",
        "heart": true,
        "reply": false,
        "time_parsed": 1623051336.732163
    },
    {
        "cid": "UgzeVPlpThuSQsb6Ve94AaABAg",
        "text": "Thank you abello for all your educational approach",
        "time": "4 years ago",
        "author": "@osmanmoha-u4q",
        "channel": "UCLVBr42XW2G4pBYbuRs4zZw",
        "votes": "3",
        "replies": "",
        "photo": "https://yt3.ggpht.com/I8zZnYXyo6sIsI8zhC5CCoGfEtZRxTm0F2OrOmhS367SQEG6rqbJdWZ9BR3NX3yLli201f6nrA=s88-c-k-c0x00ffffff-no-rj",
        "heart": false,
        "reply": false,
        "time_parsed": 1623051336.73439
    },
    {
        "cid": "UgwBdZZR0sTrfXlnGdR4AaABAg",
        "text": "Thank you \nAnte ken sew geta eyesus betehen bebreket yemulaw\nWell done!!\nKeep on teaching your knowledge \nSelam le ETHIOPIA le agre",
        "time": "4 years ago",
        "author": "@selamawitmakonnen9512",
        "channel": "UCn9GMrPGwyx1XqdLCEFLj2g",
        "votes": "3",
        "replies": "",
        "photo": "https://yt3.ggpht.com/ytc/AIdro_kkjozgyCaB2Ky1m-ozMHMFChICNUWzt4NespD42kE=s88-c-k-c0x00ffffff-no-rj",
        "heart": false,
        "reply": false,
        "time_parsed": 1623051336.736611
    },
    {
        "cid": "UgzDdQEHt7_N7KE7HqV4AaABAg",
        "text": "ብርታ አናመሠግናለን❤❤",
        "time": "1 month ago",
        "author": "@خديجة-س9ع4ف",
        "channel": "UCYMuJLxpkrXBKaJWL3iYsAw",
        "votes": "0",
        "replies": "",
        "photo": "https://yt3.ggpht.com/5hTvBT3B3_YUliw75LmnTRcEx9vLFjC83t9kmOOr117y6E48mErguJx23ftpOROe-gj905e67Q=s88-c-k-c0x00ffffff-no-rj",
        "heart": false,
        "reply": false,
        "time_parsed": 1746603336.740262
    },
    {
        "cid": "UgzCuKchiG7m7PM6BJB4AaABAg",
        "text": "Wow dear Abel very very useful. All the example you gave made it very easy to understand. Such a detailed explanation. Thank you dear so very much.",
        "time": "4 years ago",
        "author": "@lilymulugeta6824",
        "channel": "UCaQ26dwLkvHrwhdzJXBSH4w",
        "votes": "2",
        "replies": "",
        "photo": "https://yt3.ggpht.com/dbQTEM-V192PaMuD4RDtboLV6oxPZU4heY7Fh7VyhY_ihLaeT9dq0TD85nmb-5HF3j2fgyb7Jg=s88-c-k-c0x00ffffff-no-rj",
        "heart": false,
        "reply": false,
        "time_parsed": 1623051336.742656
    },
    {
        "cid": "Ugy7xKbVGnp7zlKHDWB4AaABAg",
        "text": "ሰላም ውድ የኢትዮጵያ ቤተሰቦች ምንያህል እንደምወዳቹ ታውቃላቹ አይደል ይህን የስዕል ቻናሌን ሰብስክራይብ በማድረግ አበረታቱኝ plsssssssssssss እንዲሁም አስተያየት በመስጠት እንዳድግ አግዙኝ abel birhanu እንዲ ተስሏል @",
        "time": "4 years ago",
        "author": "@damartsstudio7115",
        "channel": "UCEfZmHJg79SEYwSFlGmaGeA",
        "votes": "4",
        "replies": "",
        "photo": "https://yt3.ggpht.com/n4VjnSZtqhORRuw-IO5vzJUPjz4t8AGWbnyMsaO8c3c1BQmrXx6lLVG0v2qNCf_Fcn17zLL0=s88-c-k-c0x00ffffff-no-rj",
        "heart": false,
        "reply": false,
        "time_parsed": 1623051336.744982
    },
    {
        "cid": "UgyF2MoDQHfaLhJc2qJ4AaABAg",
        "text": "Thank you very mach",
        "time": "4 years ago",
        "author": "@ephremseyoum2790",
        "channel": "UCrpguzEqN4iaVJpqYe-3kRA",
        "votes": "0",
        "replies": "",
        "photo": "https://yt3.ggpht.com/ytc/AIdro_kHPovXr0vb_hk79JTIDd5g_YmbxdwZkAvP0cVEKG_H5FA=s88-c-k-c0x00ffffff-no-rj",
        "heart": true,
        "reply": false,
        "time_parsed": 1623051336.747285
    },
    {
        "cid": "UgyLC7FlkSa1fJa9voF4AaABAg",
        "text": "ምርጥ መረጃ ነው አቤሎ እናመሰግናል ግን አንዳድ ሚረብሹ ሳውንድ ኢፌክቶች አሉ ቢቀሩ ምርጥ ነው",
        "time": "3 months ago",
        "author": "@BetegnaMultimedia1",
        "channel": "UCfoU0gIs_yoJQtprlnetAKw",
        "votes": "0",
        "replies": "",
        "photo": "https://yt3.ggpht.com/7GmTe04Rpx2EoxAkqqo_HbljSOT_r542Zqz_ZbHk1RxoGULDBzyNCXwk_rEwMSi-Gxuthlp3tgc=s88-c-k-c0x00ffffff-no-rj",
        "heart": false,
        "reply": false,
        "time_parsed": 1741332937.061454
    },
    {
        "cid": "Ugz0kBN-itvNZL8Di5N4AaABAg",
        "text": "Balefo tik Tok lay electric yezosh neber terefel gin 😆",
        "time": "4 years ago",
        "author": "@LucyTip",
        "channel": "UCuK5LYbB6XuuOeo3LQzP5Bg",
        "votes": "3",
        "replies": "",
        "photo": "https://yt3.ggpht.com/I1NTdOMOQk4j40rcfsXQXYk4Z0PEY6aWTV7t2gEyyBSRhg8XeeUJW-XtsnWhdDMuMRPQdpsbJw=s88-c-k-c0x00ffffff-no-rj",
        "heart": true,
        "reply": false,
        "time_parsed": 1623051337.063939
    },
    {
        "cid": "UgzSFW7da5qXzwmgp9l4AaABAg",
        "text": "thank u bro, u r inspirational",
        "time": "2 years ago",
        "author": "@roberaengineer9066",
        "channel": "UCvsxb8pQohplrUeJfl8xeEA",
        "votes": "1",
        "replies": "",
        "photo": "https://yt3.ggpht.com/ytc/AIdro_kICLEWVz_Df11W9j2QDfrHNDDg1x_VaLwS8b0VSK2HbsRDCJlZlRWUA-jL7XAQ5mwfAg=s88-c-k-c0x00ffffff-no-rj",
        "heart": false,
        "reply": false,
        "time_parsed": 1686123337.066733
    },
    {
        "cid": "UgzYPRuCP0EUOxyncOd4AaABAg",
        "text": "and thanks",
        "time": "4 years ago",
        "author": "@thed7751",
        "channel": "UCTa_5XLfvV6nHgmQWGdCP6A",
        "votes": "0",
        "replies": "",
        "photo": "https://yt3.ggpht.com/ytc/AIdro_mNe8iD1K_rzUj11DAuCEIJgOurjZh-g7jSgQmDyX0e36g=s88-c-k-c0x00ffffff-no-rj",
        "heart": false,
        "reply": false,
        "time_parsed": 1623051337.069382
    },
    {
        "cid": "UgzMcGW0SF4JAwHP9Nt4AaABAg",
        "text": "Betam tanks",
        "time": "2 years ago",
        "author": "@Tngert",
        "channel": "UCSXjf-goGsgY-DMPefiEqzg",
        "votes": "0",
        "replies": "",
        "photo": "https://yt3.ggpht.com/-26scG1cAnCrokEoZcV6S8WKfW5apeW2fB2rjCExQbnYzwZnIw1wC2TAXkv48TLNfvw5zuevyA=s88-c-k-c0x00ffffff-no-rj",
        "heart": false,
        "reply": false,
        "time_parsed": 1686123337.071689
    },
    {
        "cid": "UgxbOJ02YrW8XBWiUWZ4AaABAg",
        "text": "ጀግና በርታ",
        "time": "11 months ago",
        "author": "@BineBine-kj4yy",
        "channel": "UCvNb9qUqQg-pZgD7VAMjAKQ",
        "votes": "0",
        "replies": "",
        "photo": "https://yt3.ggpht.com/R77r2afwn9DsUVXrZVE_s3x6YudRXMwflqMyskQi5LDZiKFsaPP8E88vq8DWtmoUtMph1kCV1g=s88-c-k-c0x00ffffff-no-rj",
        "heart": false,
        "reply": false,
        "time_parsed": 1720337737.075249
    },
    {
        "cid": "Ugyj9Xwv20be0RSYOLR4AaABAg",
        "text": "Tnxs btam sflgaw",
        "time": "4 years ago",
        "author": "@yohannestemsgen288",
        "channel": "UCx5sbxtdbyscIabc7ryta6g",
        "votes": "1",
        "replies": "",
        "photo": "https://yt3.ggpht.com/ytc/AIdro_ncwuZLpWdCRLnQCMMkpnE04vHzC4etUY-VlcaZtdOORg=s88-c-k-c0x00ffffff-no-rj",
        "heart": true,
        "reply": false,
        "time_parsed": 1623051337.077543
    },
    {
        "cid": "Ugy2G6UddfW0G9t8PYt4AaABAg",
        "text": "Abel ከቅርብ ጊዜ በኃላ የዩቲዩብ ቻናሌ ምን እንደሆነ views ሊያገኝ አልቻለም ምን ላድርግ ወንድሜ ቀጣይ video ስራልኝ በናትህ🙏🙏🙏",
        "time": "1 year ago",
        "author": "@Rakebtamrat1661",
        "channel": "UCDigWoLRlM-IRB1bJeJ3UgQ",
        "votes": "1",
        "replies": "",
        "photo": "https://yt3.ggpht.com/SqQmeDGnlvqMpdeKy7jweXLLREaRve2JL7OutXYHFgvI1ZUMYlztvsrXDnVha7yG58tCSvCF=s88-c-k-c0x00ffffff-no-rj",
        "heart": false,
        "reply": false,
        "time_parsed": 1717745737.08094
    },
    {
        "cid": "Ugy3NX0QYD-a13HNnl14AaABAg",
        "text": "Thank u brother",
        "time": "7 months ago",
        "author": "@MikaelBerhane12",
        "channel": "UCz0GJ14n4lHQBFPxhnL1v3g",
        "votes": "0",
        "replies": "",
        "photo": "https://yt3.ggpht.com/ysI_AHMqrS2pZp8ZqpJ_lokYu4WahoLhD88EI-edgbh1M2iinYW2b22bxOx6ZHw5WN4hh-iXAtQ=s88-c-k-c0x00ffffff-no-rj",
        "heart": false,
        "reply": false,
        "time_parsed": 1730964937.084737
    },
    {
        "cid": "UgxQs61YSxC9WjXEP754AaABAg",
        "text": "Thanks abel 🤝🙏",
        "time": "11 months ago",
        "author": "@Starboyendax",
        "channel": "UCkLI3ROOSdIFsiOUzm3g8RQ",
        "votes": "0",
        "replies": "",
        "photo": "https://yt3.ggpht.com/AKZZyQZIY1pK3hVRErtEo5flpnFK3UWR9D1pf1-DzVvfrkiVt0054t6-1IpGlGh-vg5AWktd2w=s88-c-k-c0x00ffffff-no-rj",
        "heart": false,
        "reply": false,
        "time_parsed": 1720337737.088328
    },
    {
        "cid": "Ugx3bLWuVjfz89X3__p4AaABAg",
        "text": "Nice vid tnx  Profitable niche yemitlewn video bitseralen kechalk!",
        "time": "4 years ago",
        "author": "@zekariyasberihun8093",
        "channel": "UCmgKGU1z2VkC6Qk2JaEHjVQ",
        "votes": "0",
        "replies": "",
        "photo": "https://yt3.ggpht.com/ytc/AIdro_lKwAs9cOx1v7d7ATxlD6R-Gu0tgpNtKXm2LQ_uwJ8Cgw=s88-c-k-c0x00ffffff-no-rj",
        "heart": true,
        "reply": false,
        "time_parsed": 1623051337.09089
    },
    {
        "cid": "UgzBKXyYMqURClP78ol4AaABAg",
        "text": "Good idea",
        "time": "4 years ago",
        "author": "@mustajibfikadu5507",
        "channel": "UC6zRgFLvsPU3epg-ddRQogA",
        "votes": "0",
        "replies": "",
        "photo": "https://yt3.ggpht.com/ytc/AIdro_kEFWI-Ac-Eazm5-sjrVoUgmZ6CS9WStF-8_ACmaO1tdJk=s88-c-k-c0x00ffffff-no-rj",
        "heart": true,
        "reply": false,
        "time_parsed": 1623051337.093209
    },
    {
        "cid": "UgysQ1X_VW_GZlTOp2J4AaABAg",
        "text": "VERY NICE MY BRO\n\nGOD BLESS YOU 💚",
        "time": "4 years ago",
        "author": "@Burike9",
        "channel": "UCzimBm2QCXq-F6CsSvsGdjg",
        "votes": "4",
        "replies": "",
        "photo": "https://yt3.ggpht.com/3FsQfpuFAS6SLRhQLQ61VddGGhzCx0HfjxtSy-dxBWfTo4J2yF6prET9FFsxCsMvm49CI90T=s88-c-k-c0x00ffffff-no-rj",
        "heart": false,
        "reply": false,
        "time_parsed": 1623051337.095597
    },
    {
        "cid": "UgyMFvNZFO7fVF7141V4AaABAg",
        "text": "ጤና ይስጥልኝ ሚዲያ አገልግሎት እንኳን ለኢትዮጵያ 2013 ዓ/ም አደረሳችሁ እያለ ሰላምን ደስታን ፍቅርን እየተመኘላችሁ ጤና ይስጥልኝ ይላችኋል የዩቲዩብ መስመራችንን ገብተው ቤተሰብ እንዲሆኑን እንጋብዛችኋለን መልካም 2013 ዓ/ም",
        "time": "4 years ago",
        "author": "@kassuboston",
        "channel": "UCXQeAJgDLecjaAb_7ZjJmoA",
        "votes": "1",
        "replies": "",
        "photo": "https://yt3.ggpht.com/ytc/AIdro_n-9QpX_lMfuvS9ah4pzS7ktKk0aCX8iUXBufUAMFBGRCJP=s88-c-k-c0x00ffffff-no-rj",
        "heart": true,
        "reply": false,
        "time_parsed": 1623051337.099402
    },
    {
        "cid": "Ugz3OPRdz0EI-0PKBXF4AaABAg",
        "text": "አንደኛህ ኮሜት ስለሆኩ pin አልብሰኝ አቤሎ",
        "time": "4 years ago",
        "author": "@LijTofik",
        "channel": "UC7AyBb5d64bN0h5cwnOy4BA",
        "votes": "6",
        "replies": "7",
        "photo": "https://yt3.ggpht.com/ZXyULe7sk23uLK2LAkRTjzYz4BEx3hROv0FDGpvDczbOXt8CiiwCcfJPFCF-dwe8Y5Nnv7po=s88-c-k-c0x00ffffff-no-rj",
        "heart": true,
        "reply": false,
        "time_parsed": 1623051337.101837
    },
    {
        "cid": "UgwM-46LwjPjnvRjs_h4AaABAg",
        "text": "በቁስና በአለባበስ  ምንትላለይ❤❤❤😂",
        "time": "3 weeks ago",
        "author": "@GetuEshetu-c9x",
        "channel": "UC0JOlXHjDVZYXruEnmKurzw",
        "votes": "0",
        "replies": "",
        "photo": "https://yt3.ggpht.com/ytc/AIdro_khmeWaPqEFFNXiWHgSHpRCJDmCuWJlirCk_lVQBtJeUPF1q8TvwiBHuhZs6LI5d8ldPg=s88-c-k-c0x00ffffff-no-rj",
        "heart": false,
        "reply": false,
        "time_parsed": 1747467337.104333
    },
    {
        "cid": "UgyBcF8J1pn0RU782C94AaABAg",
        "text": "Abelo arif ....enamesegnaln",
        "time": "4 years ago",
        "author": "@natnaeldagnee",
        "channel": "UCsfT0A5by7QWuWoHQBPeuwA",
        "votes": "0",
        "replies": "1",
        "photo": "https://yt3.ggpht.com/N8JpfM3KAaCfRh_eSnBiHL_QIZby45C1pEG2FzR4P6lU0j0PDUq9xrngyk0QqOsrK9IAqmHvjTg=s88-c-k-c0x00ffffff-no-rj",
        "heart": true,
        "reply": false,
        "time_parsed": 1623051337.107589
    },
    {
        "cid": "UgwuiqV7jjRiCCgrXXF4AaABAg",
        "text": "It was very helpful thank you\nKeep up the good work",
        "time": "1 year ago",
        "author": "@adanealemayehu5903",
        "channel": "UCdK5-ig-8UNEghZVPANHMxg",
        "votes": "0",
        "replies": "",
        "photo": "https://yt3.ggpht.com/ytc/AIdro_mKAQ0-ZPtME9bdJQUmxQsDlH_dvLQf6XbQzeJ7WTnsYZY=s88-c-k-c0x00ffffff-no-rj",
        "heart": false,
        "reply": false,
        "time_parsed": 1717745737.110367
    },
    {
        "cid": "UgyyNWSCrvBbWAfgKLd4AaABAg",
        "text": "እናመሰግናለን ወድማችን \nየተዋህዶ ልጆች በቅንንት ሰብስክራይብ አስጉኝ በየለቱ የሚነበቡትን ወንጌል እያነበብኩ አቀርባለዉ እና መፈሳዊ ነገር አቀርባለዉ",
        "time": "4 years ago",
        "author": "@መሲየድንግልልጅነኝዩቱብ",
        "channel": "UC7ZcmsC5PaELT_q0cnXaGmg",
        "votes": "7",
        "replies": "",
        "photo": "https://yt3.ggpht.com/ytc/AIdro_lLL7iUQGhdmHCltrrzgM4HuXjDPF_2WFKozBQ0DphWTQ=s88-c-k-c0x00ffffff-no-rj",
        "heart": true,
        "reply": false,
        "time_parsed": 1623051337.112622
    },
    {
        "cid": "Ugz8h0z2VYMqXqzk1ah4AaABAg",
        "text": "Abelo bnka ejhi esky vidochin shere btderglin btsdgn mlkiam new  kmadm madbti endinwta  😂😂😂😂",
        "time": "4 years ago",
        "author": "@sehenyee",
        "channel": "UCJZJJFahFD1SbMGU5sPFcUQ",
        "votes": "0",
        "replies": "",
        "photo": "https://yt3.ggpht.com/9T-qy5d1Ea_KXJNqGJ-F6rhbykYz7lBIZgIluzeITKyReMdshCfrEWmLIIfxf02AQv9nU7TvElI=s88-c-k-c0x00ffffff-no-rj",
        "heart": true,
        "reply": false,
        "time_parsed": 1623051337.115073
    },
    {
        "cid": "Ugz3OPRdz0EI-0PKBXF4AaABAg.9DXxSkGm8hb9DXx_ZOAgQG",
        "text": "😀😀😀ተቀድመሃል",
        "time": "4 years ago",
        "author": "@ጌጤእህተማርያምጉዞወደእማ",
        "channel": "UCUKJtN_CxgN1xPrjUQ7bCxQ",
        "votes": "0",
        "replies": "",
        "photo": "https://yt3.ggpht.com/C5YPzDh0plGGTcySnSzhRLUsEG_ClB-p5KAOJbPydXM-g8j9YUXxGvJ8FwJ5LuDxy1gIXqem=s88-c-k-c0x00ffffff-no-rj",
        "heart": false,
        "reply": true,
        "time_parsed": 1623051337.390745
    },
    {
        "cid": "Ugz3OPRdz0EI-0PKBXF4AaABAg.9DXxSkGm8hb9DXyoKhEIsA",
        "text": "ጎበዝ ልጅ ነህ አተም በርታ ቶፊቄ",
        "time": "4 years ago",
        "author": "@ኢማንየሱምርኮኛ",
        "channel": "UCwzGabnN4J78qPYp7F1ZOWQ",
        "votes": "0",
        "replies": "",
        "photo": "https://yt3.ggpht.com/ytc/AIdro_nrJWSKHQqFOmMAuEh0SDfFbmV224IZfPDKkgfmlCo=s88-c-k-c0x00ffffff-no-rj",
        "heart": false,
        "reply": true,
        "time_parsed": 1623051337.39308
    },
    {
        "cid": "Ugz3OPRdz0EI-0PKBXF4AaABAg.9DXxSkGm8hb9DXzIFl-BLM",
        "text": " @Afro_sport  አዎ ያሳዉቃሉ ጥንቃቄ ማረግ አለባችሁ",
        "time": "4 years ago",
        "author": "@LijTofik",
        "channel": "UC7AyBb5d64bN0h5cwnOy4BA",
        "votes": "0",
        "replies": "",
        "photo": "https://yt3.ggpht.com/ZXyULe7sk23uLK2LAkRTjzYz4BEx3hROv0FDGpvDczbOXt8CiiwCcfJPFCF-dwe8Y5Nnv7po=s88-c-k-c0x00ffffff-no-rj",
        "heart": false,
        "reply": true,
        "time_parsed": 1623051337.398029
    },
    {
        "cid": "Ugz3OPRdz0EI-0PKBXF4AaABAg.9DXxSkGm8hb9DY0otbM3VF",
        "text": "Eski na enzamed",
        "time": "4 years ago",
        "author": "@BigChallenge1",
        "channel": "UC9aIdmRry64qR68zFPGeevg",
        "votes": "0",
        "replies": "",
        "photo": "https://yt3.ggpht.com/gvjsWAjCZWS0QPfowrswoVOIcj9W1G0m4mY1L7nv-ZL9vjBLrrspMz9lfQgE_MSc5MrYW_694VE=s88-c-k-c0x00ffffff-no-rj",
        "heart": false,
        "reply": true,
        "time_parsed": 1623051337.400298
    },
    {
        "cid": "Ugz3OPRdz0EI-0PKBXF4AaABAg.9DXxSkGm8hb9DY0qz7QAp_",
        "text": "Enem kora llh new",
        "time": "4 years ago",
        "author": "@BigChallenge1",
        "channel": "UC9aIdmRry64qR68zFPGeevg",
        "votes": "0",
        "replies": "",
        "photo": "https://yt3.ggpht.com/gvjsWAjCZWS0QPfowrswoVOIcj9W1G0m4mY1L7nv-ZL9vjBLrrspMz9lfQgE_MSc5MrYW_694VE=s88-c-k-c0x00ffffff-no-rj",
        "heart": false,
        "reply": true,
        "time_parsed": 1623051337.402463
    },
    {
        "cid": "Ugz3OPRdz0EI-0PKBXF4AaABAg.9DXxSkGm8hb9DYJ0JyHYo4",
        "text": " @BigChallenge1  እንደመርር",
        "time": "4 years ago",
        "author": "@kedyetube4847",
        "channel": "UCo-jrkxHTIbDOTdJ-FLCc7Q",
        "votes": "0",
        "replies": "",
        "photo": "https://yt3.ggpht.com/ytc/AIdro_kLNnakF45_-YywLRLaAw268sc2M1QrMnF8JUwSmOEXPcs=s88-c-k-c0x00ffffff-no-rj",
        "heart": false,
        "reply": true,
        "time_parsed": 1623051337.404597
    },
    {
        "cid": "Ugz3OPRdz0EI-0PKBXF4AaABAg.9DXxSkGm8hb9DgwenAE3oL",
        "text": "እንደማመር",
        "time": "4 years ago",
        "author": "@እሙኢምራንየሀይቅልጅ",
        "channel": "UCTlf5yBzdD62XMVqQrcFsmw",
        "votes": "0",
        "replies": "",
        "photo": "https://yt3.ggpht.com/ytc/AIdro_maWKl72S6vZ7II__kBCWmFK_SpwVdzWtc59TF8NfU=s88-c-k-c0x00ffffff-no-rj",
        "heart": false,
        "reply": true,
        "time_parsed": 1623051337.406716
    },
    {
        "cid": "UgyBcF8J1pn0RU782C94AaABAg.9DY8-N1ieCw9DYJTpbvR-Y",
        "text": "እንደመርር ኑኑ",
        "time": "4 years ago",
        "author": "@kedyetube4847",
        "channel": "UCo-jrkxHTIbDOTdJ-FLCc7Q",
        "votes": "0",
        "replies": "",
        "photo": "https://yt3.ggpht.com/ytc/AIdro_kLNnakF45_-YywLRLaAw268sc2M1QrMnF8JUwSmOEXPcs=s88-c-k-c0x00ffffff-no-rj",
        "heart": false,
        "reply": true,
        "time_parsed": 1623051337.577493
    },
    {
        "cid": "UgyDsEoADViyWS6RllB4AaABAg",
        "text": "👍👍👍👍",
        "time": "4 years ago",
        "author": "@ramlaabdulla9265",
        "channel": "UCmfZ3sWfBXwvVeVi0tmRYkg",
        "votes": "1",
        "replies": "",
        "photo": "https://yt3.ggpht.com/ytc/AIdro_nqs5Um2V4Yw8MS5US_a2_fnAM0tpFZbrvID2dOpf8=s88-c-k-c0x00ffffff-no-rj",
        "heart": true,
        "reply": false,
        "time_parsed": 1623051337.94431
    },
    {
        "cid": "UgyyLg5uYJ0utGj7uop4AaABAg",
        "text": "Txs",
        "time": "2 years ago",
        "author": "@loconati2500",
        "channel": "UCnJaZPsLzPGMDzc5NgUhmoA",
        "votes": "0",
        "replies": "",
        "photo": "https://yt3.ggpht.com/nD8p74w9omNBUA8SrUnCXSv0eg8AO41fokNItrJ3aIo_TULKIyZi42I4ZyR06BcQEkinEr0AQao=s88-c-k-c0x00ffffff-no-rj",
        "heart": false,
        "reply": false,
        "time_parsed": 1686123337.946631
    },
    {
        "cid": "UgwAM1tKseDoAeRBP694AaABAg",
        "text": "Welcome abelisha",
        "time": "2 years ago",
        "author": "@daniteckcstube",
        "channel": "UCL2xk41eUo7CD1qAogXJ47Q",
        "votes": "0",
        "replies": "",
        "photo": "https://yt3.ggpht.com/ejpz4zcqsrK4Rw-EuDIZc4RYOf6TudSkW2Xb2CqND0bOeCZuF4LmpJozDu6Bj8BRzIS7_g6fev4=s88-c-k-c0x00ffffff-no-rj",
        "heart": false,
        "reply": false,
        "time_parsed": 1686123337.948901
    },
    {
        "cid": "UgzyhBZZDvPWg9bkZzR4AaABAg",
        "text": "እንኳን ለአዲሱ አመት አደረሳችሁ! አዲሱ አመት የሰላም፣ የጤና እና የብልፅግና ይሁንልን! የኢትዮጵያን ሰላም፣ ፍቅር እና አንድነት የሚያደፈርሱት የሚጠፉበት ዘመን ይሁንልን! 💚💛❤✔💯❗",
        "time": "4 years ago",
        "author": "@EthiopiaPost",
        "channel": "UChpzLYGJ82bww3eArzZVZvQ",
        "votes": "6",
        "replies": "2",
        "photo": "https://yt3.ggpht.com/Q3cRA1cp88aibIPkgwJDFfJq8CFHBBdAyZcVCOtU0zQkuv19Iuv3NiDRmHK9EGZpysi_OQq-8r8=s88-c-k-c0x00ffffff-no-rj",
        "heart": true,
        "reply": false,
        "time_parsed": 1623051337.951382
    },
    {
        "cid": "Ugx657WH6erQu4xnsKN4AaABAg",
        "text": "መልካም አዲስ አመት .🌻🌻🌻\nአዲሱን አመት የሰላም የፍቅር እና ያንድነት ያርግልን 🌻🌻🌻\nሰብስክራይብ ላይክ እና ሼር በማድረግ ቤተሠብ ይሁኑ💚💛❤️ \nhttps://youtu.be/a8yDh0GtqSM",
        "time": "4 years ago",
        "author": "@eskuschoice1730",
        "channel": "UCIh_ZA9suOXgdrcx5PuxTJw",
        "votes": "3",
        "replies": "",
        "photo": "https://yt3.ggpht.com/ytc/AIdro_l5rcEjTOsbyCLNnxWKUow6rxpjhSlHXAorsXnXx2Ko5qs=s88-c-k-c0x00ffffff-no-rj",
        "heart": true,
        "reply": false,
        "time_parsed": 1623051337.953716
    },
    {
        "cid": "UgzIrUwnku-Ol5po2q94AaABAg",
        "text": "በጣም ጠቃሜ ትምህርት ነው መልካም ፍቃድህ ከሆነ አንድ ነገር ብታብራራልኝ እኔ አንድ ነጠላ ዜማ ስርቸ  ለ6ወር  ሆፕ ላይ ጭኔው ነበር ውላችን ደግሞ ለ6ወር ነበር እነሱም ተገቢውን ክፍያ ስላልከፈሉኝ አሁን ከራሴ ቻናል መልቀቅ ፈልጌ ነበር ምን ማድርግ እንዳሉብኝ ብታብራራልኝ ደስ ይለኛል 🙏🙏🙏🙏🙏",
        "time": "4 years ago",
        "author": "@Mesi89",
        "channel": "UCzGGuocPHNG415sIvdUIpqg",
        "votes": "0",
        "replies": "",
        "photo": "https://yt3.ggpht.com/oKMqyzM0YKc8UMUmbefUNZfvL6v4bYdXu3r_apZQugHVtOVl8N2y9V5wc9rHkvuDIgaB4pJoE0U=s88-c-k-c0x00ffffff-no-rj",
        "heart": false,
        "reply": false,
        "time_parsed": 1623051337.956002
    },
    {
        "cid": "UgxBPBR1A0yjH5_5uyB4AaABAg",
        "text": "እኔ የምለው አቤሎ 🤔የተጠቆርክበትን ቪዲዮ ብትደልተውስ ይፋቱሀል? ወይንስ አይሰሙህም??????🤔🤔🤔",
        "time": "4 years ago",
        "author": "@egziabhermastewalunyisten7704",
        "channel": "UC9lczueOmW848n8Dz6qqqng",
        "votes": "11",
        "replies": "2",
        "photo": "https://yt3.ggpht.com/a9GJfRXP-bLdL20VaVeCfSvHmy1Q3qWomrV3wFSF6VbCIOslr7iR5WNWDPbClLOjA0LTFa49jg=s88-c-k-c0x00ffffff-no-rj",
        "heart": true,
        "reply": false,
        "time_parsed": 1623051337.958258
    },
    {
        "cid": "Ugxp_oIw1ZBT-uI2_y94AaABAg",
        "text": "ምርጥ ልጅ ነህ አቤላ ከድሮም ነው ዝም ብየ የምወድህ ትመቼኛለህ!!  አምናለሁ አንድ ቀን እንዳንተ ጀግ ና ዩቱዩቨር እሆናለሁ!!1!\n\nhttps://www.youtube.com/channel/UCQFXIdXUo9voko-qkDBrUCQ/",
        "time": "4 years ago",
        "author": "@JOYO545-JO",
        "channel": "UCQFXIdXUo9voko-qkDBrUCQ",
        "votes": "4",
        "replies": "",
        "photo": "https://yt3.ggpht.com/3yoGC1s3c3Ak1Wj8vkBSRRLLuicHszYM7PxLaYYcqzxbCanUSQSt4ebtYDkzkzSPxcyY9GHbdA=s88-c-k-c0x00ffffff-no-rj",
        "heart": false,
        "reply": false,
        "time_parsed": 1623051337.960449
    },
    {
        "cid": "UgxcoHXJm5TsQNkSnxp4AaABAg",
        "text": "Ere mezmurs mezemer anchilm malet new?????",
        "time": "4 years ago",
        "author": "@ethiochewata",
        "channel": "UCJXCTCITzqawmpZ-XQNRy3w",
        "votes": "0",
        "replies": "",
        "photo": "https://yt3.ggpht.com/ytc/AIdro_k4__mVr4wjOWCQ-_Hd3quolF0zDcfDQuDCN2Ly6tMUiw=s88-c-k-c0x00ffffff-no-rj",
        "heart": false,
        "reply": false,
        "time_parsed": 1623051337.962677
    },
    {
        "cid": "UgwUSd4dI6hFOIgEGil4AaABAg",
        "text": "yelela sewn sera degame post bedereg...birr ayasgegnim enj channelun yazegal ende?",
        "time": "4 years ago",
        "author": "@abdirection5107",
        "channel": "UCV8tGTa55QzG_JjHvrAecjw",
        "votes": "1",
        "replies": "",
        "photo": "https://yt3.ggpht.com/ytc/AIdro_k-Ui7-GmAABbVb-Kf_CsR4Z_BAoVydtBqfGWgdIkcAXCo=s88-c-k-c0x00ffffff-no-rj",
        "heart": true,
        "reply": false,
        "time_parsed": 1623051337.964825
    },
    {
        "cid": "UgzirsCUnLODbXkJjJt4AaABAg",
        "text": "I like it",
        "time": "1 year ago",
        "author": "@millionpetrosworld",
        "channel": "UCt0cLYjDhcIeKHrCI-r6DLA",
        "votes": "0",
        "replies": "",
        "photo": "https://yt3.ggpht.com/DCTzGgL-js18OZpfD8yHH-lKZJY32AxevpwJ7F_E8jpJdzfhAmg5klTnGRZ_AJbFx1AG-S2Pf24=s88-c-k-c0x00ffffff-no-rj",
        "heart": false,
        "reply": false,
        "time_parsed": 1717745737.966973
    },
    {
        "cid": "UgxIdZ4LwaTwvtzM3JZ4AaABAg",
        "text": "Wow Abelo tekam newu betam",
        "time": "4 years ago",
        "author": "@biniyamworkneh5888",
        "channel": "UCKugGouHOhybjZ83ylToOmA",
        "votes": "0",
        "replies": "",
        "photo": "https://yt3.ggpht.com/ytc/AIdro_nfGVufQHazf0eITPvCUI7SQNKSAClG0vvIzlNRE6wnNFs=s88-c-k-c0x00ffffff-no-rj",
        "heart": true,
        "reply": false,
        "time_parsed": 1623051337.969143
    },
    {
        "cid": "UgxL72FMY16WYYSlQuJ4AaABAg",
        "text": "Music video senetekems esun satasayen.....",
        "time": "4 years ago",
        "author": "@novatube1956",
        "channel": "UC8HuuIilD6OICLnU98MllvA",
        "votes": "0",
        "replies": "",
        "photo": "https://yt3.ggpht.com/u1gSOK1US96LJwS7A8M_c_ZmwIghw54JDKW2Ck6oB_rJRGsKqnXFPnzJlAWlKiKvzFex8U_eJQ=s88-c-k-c0x00ffffff-no-rj",
        "heart": false,
        "reply": false,
        "time_parsed": 1623051337.971288
    },
    {
        "cid": "Ugz1hHNu3ABR3V9xeON4AaABAg",
        "text": "Wow",
        "time": "1 year ago",
        "author": "@Habshaw",
        "channel": "UCLtgjjaEYFh8QQk6eHr8T_A",
        "votes": "0",
        "replies": "",
        "photo": "https://yt3.ggpht.com/LhNI5cxc9eFZGyUO8CBtyqbq9hSURLOzytgyzNr-AeWQroy3OdGHncks-9MYC_l1dwdrAhIQ=s88-c-k-c0x00ffffff-no-rj",
        "heart": false,
        "reply": false,
        "time_parsed": 1717745737.973407
    },
    {
        "cid": "UgyCDZuo5wxO-BQbhuR4AaABAg",
        "text": "how to remove copyright claim on lyric video plz  abela",
        "time": "1 year ago",
        "author": "@user-alutes",
        "channel": "UCVVhXwDP-6UuSHzdJufZS3A",
        "votes": "1",
        "replies": "",
        "photo": "https://yt3.ggpht.com/vr0Sk5AUqwbIShnptfM8P_0lgt_-pAUwJmiokBwu0oAGqgLSEQYf6A_2iIdIJYH4MQmLxkqC=s88-c-k-c0x00ffffff-no-rj",
        "heart": false,
        "reply": false,
        "time_parsed": 1717745737.975517
    },
    {
        "cid": "UgxtcYpRMFkgU2RLzaN4AaABAg",
        "text": "abl እኔ የምሰራው መዝሙር ነው እና copyright ሊባል ይቻላል ? እና ስለምታስተምረን እናመሰግናለን ።😘😘",
        "time": "2 years ago (edited)",
        "author": "@lyrics-mezmur-1",
        "channel": "UCMbftzD-r8uSWcejbB_q0gA",
        "votes": "1",
        "replies": "",
        "photo": "https://yt3.ggpht.com/KgDTALmPkq7iPYR4f-YLSkKRkx4X7lW91-etgG5Oqw6TlWB1XvdppqxjApWy1nqg7ZyrmRD7h34=s88-c-k-c0x00ffffff-no-rj",
        "heart": false,
        "reply": false,
        "time_parsed": 1686123337.977642
    },
    {
        "cid": "Ugy3ydPgsRbPFy4oODZ4AaABAg",
        "text": "betam amesegnalew",
        "time": "4 years ago",
        "author": "@dreammoonstar1882",
        "channel": "UCr9w3seueTXL_Ot13fQLVbA",
        "votes": "0",
        "replies": "",
        "photo": "https://yt3.ggpht.com/yNWM3qCclE7i32zFdYO7AHD1I4ZB8j4_SXWXDX638d1haOOSWAmPOM7KkxwYi48bSwqJGJoVng=s88-c-k-c0x00ffffff-no-rj",
        "heart": true,
        "reply": false,
        "time_parsed": 1623051337.979746
    },
    {
        "cid": "UgzdiI6qKJ9pB-mqf1x4AaABAg",
        "text": "❤❤❤❤❤❤❤",
        "time": "3 months ago",
        "author": "@ዝግራሚዲያ6091",
        "channel": "UC3JymMRMZOlL3ej0P1w2eug",
        "votes": "0",
        "replies": "",
        "photo": "https://yt3.ggpht.com/LmaIC_RS0OIszawDPOEGSCQbehMQOd6KUVkbDq1ZFUHSdgPgk5oCspriAJa1FJkYmiG8RJfZ=s88-c-k-c0x00ffffff-no-rj",
        "heart": false,
        "reply": false,
        "time_parsed": 1741332937.983053
    },
    {
        "cid": "UgwTbCVuw_NL9dgsXvd4AaABAg",
        "text": "wow",
        "time": "2 years ago",
        "author": "@Right-Fun",
        "channel": "UCnH-58_Q9zktFAIaxOGUrdA",
        "votes": "0",
        "replies": "",
        "photo": "https://yt3.ggpht.com/XwQR-9mOR79yzV6Peh-6A7bt6VrWLVZ450SqsTB8UYMx1bqfoKEm9Zy9aorZErmRjiiECzjz=s88-c-k-c0x00ffffff-no-rj",
        "heart": false,
        "reply": false,
        "time_parsed": 1686123337.985194
    },
    {
        "cid": "UgzCMkuUSGNXt0TD7NN4AaABAg",
        "text": "Selam now abeliye  \n  Can i upload someone's  video,  by changing  languages to my channel  ? Or it is copyright",
        "time": "3 years ago",
        "author": "@englishtotigrigna1575",
        "channel": "UC-T-kMzpnmL4OIb2TxdHbew",
        "votes": "1",
        "replies": "",
        "photo": "https://yt3.ggpht.com/4RrmT0SFlOnv-pjnWL2dDyin1IpREz7vMID40MWUp8_1hbpdTuXB17NqpfOGdprO-vCVztrx5g=s88-c-k-c0x00ffffff-no-rj",
        "heart": false,
        "reply": false,
        "time_parsed": 1654587337.987322
    },
    {
        "cid": "UgzyhBZZDvPWg9bkZzR4AaABAg.9DXyg6_mmnp9DY60cpqU0O",
        "text": "እንደመርርር",
        "time": "4 years ago",
        "author": "@kedyetube4847",
        "channel": "UCo-jrkxHTIbDOTdJ-FLCc7Q",
        "votes": "1",
        "replies": "",
        "photo": "https://yt3.ggpht.com/ytc/AIdro_kLNnakF45_-YywLRLaAw268sc2M1QrMnF8JUwSmOEXPcs=s88-c-k-c0x00ffffff-no-rj",
        "heart": false,
        "reply": true,
        "time_parsed": 1623051338.178012
    },
    {
        "cid": "UgzyhBZZDvPWg9bkZzR4AaABAg.9DXyg6_mmnp9DZG9pEGhfA",
        "text": "አሜን አሜን አሜን",
        "time": "4 years ago",
        "author": "@eteneshyoutub4873",
        "channel": "UCXBlzeL9SEeS9Zlp0KN-QQg",
        "votes": "1",
        "replies": "",
        "photo": "https://yt3.ggpht.com/h7xvZGRlQIN3l0xFbH6ICzTr10C5kYrcfUx7bTBWA4OEA9fzscHt4rTixz8AMRviq-OqiEOm=s88-c-k-c0x00ffffff-no-rj",
        "heart": false,
        "reply": true,
        "time_parsed": 1623051338.180388
    },
    {
        "cid": "UgxBPBR1A0yjH5_5uyB4AaABAg.9DZGQfA-05vA-7WNLpWRgH",
        "text": "Awo bttatefawus",
        "time": "1 year ago",
        "author": "@KedirJemal-hv5ot",
        "channel": "UCbO_moIskvYlwV-ec3rSxJg",
        "votes": "0",
        "replies": "",
        "photo": "https://yt3.ggpht.com/zSU-a1bxsVXY2gjgyTAyc7qYkgHcn85GflnqHgL0rev8mPNbDgIxNc-7nYUK9H3Uev7DgXbiZA0=s88-c-k-c0x00ffffff-no-rj",
        "heart": false,
        "reply": true,
        "time_parsed": 1717745738.405605
    },
    {
        "cid": "UgxBPBR1A0yjH5_5uyB4AaABAg.9DZGQfA-05vAHml4FbQQHd",
        "text": "ምንድነው ይፋቱሀል ምናምን ቋንቋው ሲያስጠላ",
        "time": "1 month ago",
        "author": "@መስፍንፍቅረየሱስ",
        "channel": "UC6DJtp-8rmYA7CNYAVsSTZA",
        "votes": "0",
        "replies": "",
        "photo": "https://yt3.ggpht.com/ytc/AIdro_lb_1Uy3TdWaZLPGG3xk3SJCFjXtTLthSnx9O9nunT8E1Y=s88-c-k-c0x00ffffff-no-rj",
        "heart": false,
        "reply": true,
        "time_parsed": 1746603338.409018
    },
    {
        "cid": "UgwG30F6pWbszC0GYvh4AaABAg",
        "text": "👍👍",
        "time": "1 month ago",
        "author": "@خديجة-س9ع4ف",
        "channel": "UCYMuJLxpkrXBKaJWL3iYsAw",
        "votes": "0",
        "replies": "",
        "photo": "https://yt3.ggpht.com/5hTvBT3B3_YUliw75LmnTRcEx9vLFjC83t9kmOOr117y6E48mErguJx23ftpOROe-gj905e67Q=s88-c-k-c0x00ffffff-no-rj",
        "heart": false,
        "reply": false,
        "time_parsed": 1746603338.694926
    },
    {
        "cid": "UgwaCB24nD6uF8r2DWJ4AaABAg",
        "text": "እንዴት ነው cover Page ምታሳምረው",
        "time": "4 years ago",
        "author": "@thed7751",
        "channel": "UCTa_5XLfvV6nHgmQWGdCP6A",
        "votes": "0",
        "replies": "",
        "photo": "https://yt3.ggpht.com/ytc/AIdro_mNe8iD1K_rzUj11DAuCEIJgOurjZh-g7jSgQmDyX0e36g=s88-c-k-c0x00ffffff-no-rj",
        "heart": false,
        "reply": false,
        "time_parsed": 1623051338.696434
    },
    {
        "cid": "UgwC12Q-rcMLd3V51yh4AaABAg",
        "text": "abel Tqami vidyo nawe amsgenalhu bretalene",
        "time": "2 years ago",
        "author": "@kederawel8140",
        "channel": "UCLHvbrAC2adn53o3ATD0c0w",
        "votes": "0",
        "replies": "",
        "photo": "https://yt3.ggpht.com/m-3-TGS7ea6NDKWHgSlLWPhFIZ_T1ba5pnhhvTOV0Bsi8pTaXNWG4rUHb2oGtcJ5LSknpWcj=s88-c-k-c0x00ffffff-no-rj",
        "heart": false,
        "reply": false,
        "time_parsed": 1686123338.697775
    },
    {
        "cid": "UgyhFsbjnzwODMc5IwF4AaABAg",
        "text": "Ante hulem arif neh Allah yetbkh live stream adis slhonku techgryalhu senkaka wetnktun awtahut men tmkrgnalh",
        "time": "2 years ago",
        "author": "@emanetyounis6836",
        "channel": "UCnGhZrxFIeyvY2aAPwc6SbA",
        "votes": "0",
        "replies": "",
        "photo": "https://yt3.ggpht.com/ti-FlOpNqO6xaDo434wm0UuBo8lZsFXcZD5puJsf9jxDzQI8VRgbv7rvn9VnrUJxBRr-JwRO4po=s88-c-k-c0x00ffffff-no-rj",
        "heart": true,
        "reply": false,
        "time_parsed": 1686123338.699039
    },
    {
        "cid": "UgxscxtUTw4MA4nVOiZ4AaABAg",
        "text": "እኔ ከፍቸ ነበር ግን ቪዲዬ መልቀቅ አልቻልኩም ለምንድነው",
        "time": "3 weeks ago",
        "author": "@asherians",
        "channel": "UCyPSs0eQhh98SKoZ0M0E3Rw",
        "votes": "0",
        "replies": "",
        "photo": "https://yt3.ggpht.com/3XItdd3OXqrBgd0amHhu_UghqjcK27eAmjLTSlhuNecyPZmqK4q9jOZ06cvDvIoszzofjIOQMg=s88-c-k-c0x00ffffff-no-rj",
        "heart": false,
        "reply": false,
        "time_parsed": 1747467338.700314
    },
    {
        "cid": "Ugz1TPHV2tyowzQrOtl4AaABAg",
        "text": "አርፍ እንፍርሜሽን ነው እኔ ግን ጥያቄ አለን እኔ የራሴን ስራ ነው ይዤ የመጣውት እና ኤድት ለማድርግ kineMaster ከፍዮ ነውየምጠቀመፍ ፍሬ ክላስካል እና ወተር ማርኩን ለማጥፍት ማለት ነው እና ከአንድም ሶስቴ ኮፒ እራት መጣብኝ ስለዝ አንተ እንዳልከው ድርጅቱን ማውራት አለብ ማለት ነው ኮፒ እራይ ስሚጣ????? ከቻልክ ጥያቄሔን ብትመልስልኝ ደስ ይለኛል አመስግናለው.",
        "time": "4 years ago",
        "author": "@zedkitchen",
        "channel": "UCvHuhyW-cnlqOhMTNqA9pfQ",
        "votes": "0",
        "replies": "",
        "photo": "https://yt3.ggpht.com/0PRj7zMujuK80O8Exy2Z24YqQ4SnPtTwr0Hmfnzm2VcWAjajM-fApq5N4yQeAB0XU42Zoq2ej-k=s88-c-k-c0x00ffffff-no-rj",
        "heart": true,
        "reply": false,
        "time_parsed": 1623051338.701697
    },
    {
        "cid": "UgxzGgdojHpZXVHkSTV4AaABAg",
        "text": "Ahu ye iphone 1t pro max vido wesden be srbt  cheger alew",
        "time": "1 year ago",
        "author": "@rzttube3987",
        "channel": "UCCM0hNB1NrYL8VQPAceKj4g",
        "votes": "0",
        "replies": "",
        "photo": "https://yt3.ggpht.com/IBwbEgM0AuN_VVaqKnLIlEcECKunjZDuK63BBn1Z3esDvWJ9qwXL2rhpEitr6YonyHxnL6Gc3Fk=s88-c-k-c0x00ffffff-no-rj",
        "heart": false,
        "reply": false,
        "time_parsed": 1717745738.702953
    },
    {
        "cid": "UgzsJj-NlZVcOOzUvtd4AaABAg",
        "text": "ንገሩኝ ኮሜቶች የምታቁ  ?",
        "time": "4 years ago",
        "author": "@አይከልየጃማልጅ",
        "channel": "UCTF5yP3mOKadbmJWp7deN-w",
        "votes": "0",
        "replies": "",
        "photo": "https://yt3.ggpht.com/FOQSwZJtr_nOkqkf2fBIInJ2qalW2J3qeBLAQb05lLRFh_XDeKOj7kMfAjxjwcM3lmKE0EI1Jw=s88-c-k-c0x00ffffff-no-rj",
        "heart": false,
        "reply": false,
        "time_parsed": 1623051338.704204
    },
    {
        "cid": "UgzuXHDFPDLN4LbgoVN4AaABAg",
        "text": "How did you edit your vid",
        "time": "4 years ago",
        "author": "@boysattitude6670",
        "channel": "UC2XHd2fMOOaXDIIlNZ-CVkg",
        "votes": "0",
        "replies": "",
        "photo": "https://yt3.ggpht.com/ytc/AIdro_nE7vKlZRA6bXxdS1O74cE9tkXqzqGRCugv_fvVh0xkzQ=s88-c-k-c0x00ffffff-no-rj",
        "heart": false,
        "reply": false,
        "time_parsed": 1623051338.705438
    },
    {
        "cid": "UgynfOMiYGy7aZbi75F4AaABAg",
        "text": "አቤሎ በጣም አመሰግናለሁ እኔ የኔ ቤተሰብ የወንድሜ ሰርግ ላይ ያደረግነውን ፓርቲ ወንድሜን ለመሽኘት ቪዲዮውን የቀረስኩት እኔ እራሴ በስልኬ ነው ከዛ በኔ ቻናል ላይ አፕሎድ ሳደርግ ኮፒ ራይት ሲለኝ እንዴት በገዛ ብራሴ ቪዲዮ ኮፒራይት እባላለሁ ብዬ ጥያቄ ፈጥሮብኝ ነበር ገብቼ ሳየው ዲቴሉን ዩቱብ የመለሰልኝን አይቻለሁ ቪዲዮው ኮፒራይት ስትራይክ አይደለም ብሎ ነፃ    አድርጎት አይቻለሁ ለወደፊቱ ግን ትልቅ ትምህርትሆኖኛል በጣም አመሰግናለሁ",
        "time": "1 year ago",
        "author": "@gezahegnelambebo6691",
        "channel": "UCMEYRMHL5zOFm_mb2w0xz7w",
        "votes": "1",
        "replies": "",
        "photo": "https://yt3.ggpht.com/ytc/AIdro_kTxY5RsRcIQGqFRaglL-APpRogmFeYr47t2QD0F-4=s88-c-k-c0x00ffffff-no-rj",
        "heart": false,
        "reply": false,
        "time_parsed": 1717745738.706662
    },
    {
        "cid": "Ugw_EeE9IBrXOz93nxx4AaABAg",
        "text": "Yotuba aldge belognal mene larege abla",
        "time": "2 years ago (edited)",
        "author": "@nati-tube9173",
        "channel": "UCpD9ladte-AZexz2wZIVH4A",
        "votes": "0",
        "replies": "",
        "photo": "https://yt3.ggpht.com/N-l1kwbbu7NWWs8fOihgmrKPj8qd8cNVDO7knS3B_K3SCsnrCPEI2VGP2WEoWVznI-8tzuSnag=s88-c-k-c0x00ffffff-no-rj",
        "heart": false,
        "reply": false,
        "time_parsed": 1686123338.707879
    },
    {
        "cid": "UgxVeoZGE8rMrIGfGRV4AaABAg",
        "text": "WOW ARIF",
        "time": "2 years ago",
        "author": "@hudhudstudio",
        "channel": "UC_G1-k4mTyYadYmMQCTOc9g",
        "votes": "0",
        "replies": "",
        "photo": "https://yt3.ggpht.com/g0esL7ve8nzOjjHjABqhfhni0G08g5JLKPFm0XdYuz8dCMoyZyWlwCvC3I8ZUWQgM2Cy19RpxA=s88-c-k-c0x00ffffff-no-rj",
        "heart": false,
        "reply": false,
        "time_parsed": 1686123338.709121
    },
    {
        "cid": "Ugw0QxHobRS5l_FU-Ft4AaABAg",
        "text": "Websit lay mawred menchelewn vedio awreden metekem anchelem enda?",
        "time": "10 months ago",
        "author": "@guzopi",
        "channel": "UCXWveMlD_3BZiwMHIJSPxFw",
        "votes": "0",
        "replies": "",
        "photo": "https://yt3.ggpht.com/lzm774zfhqhQn1fgNBGQJfg8t5gPZEinRHR8K8qTislpbTIZbXR1T1V2BI99Vub6a7B5aEQ5=s88-c-k-c0x00ffffff-no-rj",
        "heart": false,
        "reply": false,
        "time_parsed": 1723016138.711387
    },
    {
        "cid": "UgwOOv-ZvjM3MuaO75d4AaABAg",
        "text": "እዴትነው ሸር የሚደረገው ንገሩኝ ያገሬ ልጆች ከፍቼ  ነበር እዴት ላሥተዋውቀው እባካችሁ ንገሩኝ አድስ ነው",
        "time": "4 years ago",
        "author": "@አይከልየጃማልጅ",
        "channel": "UCTF5yP3mOKadbmJWp7deN-w",
        "votes": "0",
        "replies": "",
        "photo": "https://yt3.ggpht.com/FOQSwZJtr_nOkqkf2fBIInJ2qalW2J3qeBLAQb05lLRFh_XDeKOj7kMfAjxjwcM3lmKE0EI1Jw=s88-c-k-c0x00ffffff-no-rj",
        "heart": false,
        "reply": false,
        "time_parsed": 1623051338.71277
    },
    {
        "cid": "Ugy3lJiNUr0-ijQdAMx4AaABAg",
        "text": "ቆይ ታምፕሌት ኮፒ ራይት አለው",
        "time": "1 year ago",
        "author": "@dagem0636",
        "channel": "UC6iRE65wV2A0lXvYQatTYiA",
        "votes": "0",
        "replies": "",
        "photo": "https://yt3.ggpht.com/b6ypYoH8PFPOt-Q4Yq0XiIt01EZ5_gWuYlCPhAbGkvn01ySi13040SFRAFQAnNOWmrZqF4pC=s88-c-k-c0x00ffffff-no-rj",
        "heart": false,
        "reply": false,
        "time_parsed": 1717745738.714067
    },
    {
        "cid": "UgysjjRmKKaokMG0Xd54AaABAg",
        "text": "ቪድዪ ራሱ ቋንቋ ቀይረን ብንጠቀም",
        "time": "5 months ago",
        "author": "@EyualNega",
        "channel": "UCOLTRjc8Hlf6RyBNWf_OHxg",
        "votes": "0",
        "replies": "",
        "photo": "https://yt3.ggpht.com/ytc/AIdro_kFKyUfpTt-g7ZZ-6LZ1sANP6791YgWTIsbAPxggknb2p4vMYee8SivclGdDEQnvFVPyg=s88-c-k-c0x00ffffff-no-rj",
        "heart": false,
        "reply": false,
        "time_parsed": 1736235338.71621
    },
    {
        "cid": "UgzNweoD1MASap_7vj94AaABAg",
        "text": "Does football  have matter",
        "time": "1 year ago",
        "author": "@TheWizardeditz",
        "channel": "UCH0jrNzkzS7zPPvSu7WhjGw",
        "votes": "0",
        "replies": "",
        "photo": "https://yt3.ggpht.com/A2YuY3jaCo2DZhMQc2bL2NR2DLm_Dqr1iVE3oempGJmx7g_ekmDxOnUZ-8qOagwyIlS0Y7QypQ=s88-c-k-c0x00ffffff-no-rj",
        "heart": false,
        "reply": false,
        "time_parsed": 1717745738.717496
    },
    {
        "cid": "Ugx2afWiixa61Zi5L5N4AaABAg",
        "text": "free templetochis abela enesum claym alachew",
        "time": "4 years ago",
        "author": "@MuziqaBet",
        "channel": "UCKFgdMjbwmyTPfZruRkhhMA",
        "votes": "1",
        "replies": "",
        "photo": "https://yt3.ggpht.com/yzlrz99k6STf99tuiml6uYWZofM6ZhGtA_EjZm11EmYeClU8oR--qWXFHGhoaHD73Dlbk1lt=s88-c-k-c0x00ffffff-no-rj",
        "heart": true,
        "reply": false,
        "time_parsed": 1623051338.718759
    },
    {
        "cid": "UgwuC7MvOPrrrqWqYlh4AaABAg",
        "text": "ቆይ ግን አቤል ባንተ video በሰራ ትጨክናለክ?ማለት copy right  ታስብለኛለክ የው idea bhion new",
        "time": "4 years ago",
        "author": "@kdzhab19",
        "channel": "UCnEizTR72FyiOhVpqCLsXuQ",
        "votes": "0",
        "replies": "",
        "photo": "https://yt3.ggpht.com/6ePQnp73HT89y2HJwdt9U0NZ1e9PDYIaMNtWr7dydQ6eKvpwjnNiM-7iaOx7_tzexz1Dp2zEPQ=s88-c-k-c0x00ffffff-no-rj",
        "heart": false,
        "reply": false,
        "time_parsed": 1623051338.720242
    },
    {
        "cid": "Ugy3vaoxLdiwCFony1h4AaABAg",
        "text": "Over lay copyright alew wey",
        "time": "11 months ago",
        "author": "@Fraol_ze",
        "channel": "UC4wXD-fFaHEZPbysVoXnv1Q",
        "votes": "0",
        "replies": "",
        "photo": "https://yt3.ggpht.com/H86DlQtocbQaR7fUY_sSuIw7f8G5yABhumZytNy4KcBj2Sw3E0jhguFNNEAIuJ9HT6KBFKQVvw=s88-c-k-c0x00ffffff-no-rj",
        "heart": false,
        "reply": false,
        "time_parsed": 1720337738.722376
    },
    {
        "cid": "UgxVhX_rEhyRYVw7a_Z4AaABAg",
        "text": "Thanks a lot.🙏 It really helps all\n you tuber's👍\nPlease Big you tuber's  help others by sharing videos they are the one  who support you to have many Subscribers🇪🇹\nIf you agree 👍",
        "time": "4 years ago",
        "author": "@letsexploretogether4512",
        "channel": "UCAc-TnLMHn2mXvaMVGsbs-w",
        "votes": "1",
        "replies": "",
        "photo": "https://yt3.ggpht.com/WzpQYl__0ROrWKQkh1Di6D5HV89oJgc1hLjYYPEYSGxr9UQ9cyDG3W4F2JvrGf68Qp82HQ_uGQ=s88-c-k-c0x00ffffff-no-rj",
        "heart": true,
        "reply": false,
        "time_parsed": 1623051338.963087
    },
    {
        "cid": "UgyW976ePUUhBuVq6Yd4AaABAg",
        "text": "አቤል እኔ ነኝ አንደኛ ቢያንስ Pin  እስቲ ቻናሌን እየው በቃ  አይተህ ብቻ ውጣ ከዛ ማይክ ሸልመኝ ኢትዮጵያ ነኝ 🇪🇹🇪🇹🇪🇹https://youtu.be/95dLUX88vE4 እንኳን አደረሳቹ በአዲሱ አመት እሲት ምርጥ ኢትዮጵያዊ እንሁን እኔን ሰብስክራይብ በማድረግ አበረታቱኝ ኢትዮጵያ ለዘለዓለም ትሳቅ ምርጦቼ።",
        "time": "4 years ago (edited)",
        "author": "@jemilaomer7175",
        "channel": "UCCiqbXaZytX7cr-GVfsnwJw",
        "votes": "9",
        "replies": "1",
        "photo": "https://yt3.ggpht.com/1D4L25BibH_QcHV7i_HTMOO61_ES4IWjWwDeg90JCMHtexmmTrCg83IkXPt_gjBsbh7q5HRi4-M=s88-c-k-c0x00ffffff-no-rj",
        "heart": false,
        "reply": false,
        "time_parsed": 1623051338.964554
    },
    {
        "cid": "Ugz_fCEUmopW4jEVn1V4AaABAg",
        "text": "https://youtu.be/aeIlN6Iz1K8 እስኪ ይማርሽ በሉኝ ውድ የሀገሬ ልጆች 😭😭",
        "time": "4 years ago",
        "author": "@hayattube4879",
        "channel": "UCyzz5fxP95C5Nz3Yy4VADVw",
        "votes": "0",
        "replies": "1",
        "photo": "https://yt3.ggpht.com/mnIJV37XPw892kamhV-vWtP3nbNn3BTapfeHXt_bCmjqi1e5mr2Zu-Mwx5t6BFcGMY7tiEk4UQ=s88-c-k-c0x00ffffff-no-rj",
        "heart": false,
        "reply": false,
        "time_parsed": 1623051338.96583
    },
    {
        "cid": "UgzjTUn1HZs--5sgnmN4AaABAg",
        "text": "ሰላም አቤሎ! በቅርቡ 1 content ላይ copyright free background music ተጠቅሜ ነበር እና copyright claim መጣብኝ ነገር ግን እንዲህ የሚል ማብራሪያ አለው\nCopyright-protected content found. The owner allows the content to be used on YouTube.\nThe Content ID claim on your video doesn't affect your channel. This is not a copyright strike.\nIf you become a member of the YouTube Partner Program, this claim may affect your ability to monetize the video.\n\n\n                                 What do you suggest I do?",
        "time": "2 years ago (edited)",
        "author": "@Guma1713",
        "channel": "UCnVt_TggpO1WmEav2gWcAfA",
        "votes": "0",
        "replies": "",
        "photo": "https://yt3.ggpht.com/73DXDPChzqUhVU4N9lKYKEmMdHaF9DJ7ham_q95E6YhyNeyKOEdrARPM6WQ-xw3LwYX1LnkDeQ=s88-c-k-c0x00ffffff-no-rj",
        "heart": false,
        "reply": false,
        "time_parsed": 1686123338.967136
    },
    {
        "cid": "UgwlqJ4vWS6Su0wbta54AaABAg",
        "text": "Mnm alg3bagm abolu",
        "time": "4 years ago",
        "author": "@BigChallenge1",
        "channel": "UC9aIdmRry64qR68zFPGeevg",
        "votes": "0",
        "replies": "",
        "photo": "https://yt3.ggpht.com/gvjsWAjCZWS0QPfowrswoVOIcj9W1G0m4mY1L7nv-ZL9vjBLrrspMz9lfQgE_MSc5MrYW_694VE=s88-c-k-c0x00ffffff-no-rj",
        "heart": true,
        "reply": false,
        "time_parsed": 1623051338.968426
    },
    {
        "cid": "Ugx0KF5u5Q7hLP1PcRV4AaABAg",
        "text": "የዛረው ደሞ ይለያሉ ሚገራርም መኪኖች ፎቶውን በመንካት በተሰብ መሆን ይችላሉ https://www.youtube.com/watch?v=26k88otG8lM",
        "time": "4 years ago",
        "author": "@topnewset",
        "channel": "UCzNHISPPUEg-FAw1xCZsWjg",
        "votes": "1",
        "replies": "2",
        "photo": "https://yt3.ggpht.com/5XYGiS7j5envO_0yYRuUWbf6ZEgP7uZp8hmlWjqpkFPMPqMEmHgrCjaf_Qf4psbPuB48OIi4hw=s88-c-k-c0x00ffffff-no-rj",
        "heart": false,
        "reply": false,
        "time_parsed": 1623051338.969651
    },
    {
        "cid": "UgxlB4YQDJt4-JgFZlx4AaABAg",
        "text": "አዲሶች  ሰብስክራይብ  እንደራረግ",
        "time": "2 months ago",
        "author": "@WerkyeDessie-n7q7h",
        "channel": "UCglWvqFxB4eLIilWKLcxy-g",
        "votes": "0",
        "replies": "",
        "photo": "https://yt3.ggpht.com/uPbsdBROUx8tUKAokMu7pin0Qy1b3oadPe8jfZZXxC86fbSFHOalwBMwh73pxuuAU0COOp_Hlw=s88-c-k-c0x00ffffff-no-rj",
        "heart": false,
        "reply": false,
        "time_parsed": 1744011338.971739
    },
    {
        "cid": "UgzNmTFM1noh7i_syzV4AaABAg",
        "text": "አበሎ በርቺልን አሪፍ ነበር  የሚገራርሙ መኪና ቢት ያገኙበታል \nአዲስ ቻናል ነው ፎቶውን በመንካት ቢተሰብ መሆን ይችህላሉ https://www.youtube.com/watch?v=FMHWuBbXQug&t=8s",
        "time": "4 years ago (edited)",
        "author": "@topnewset",
        "channel": "UCzNHISPPUEg-FAw1xCZsWjg",
        "votes": "1",
        "replies": "2",
        "photo": "https://yt3.ggpht.com/5XYGiS7j5envO_0yYRuUWbf6ZEgP7uZp8hmlWjqpkFPMPqMEmHgrCjaf_Qf4psbPuB48OIi4hw=s88-c-k-c0x00ffffff-no-rj",
        "heart": false,
        "reply": false,
        "time_parsed": 1623051338.973058
    },
    {
        "cid": "UgzBjuhpUxleX2S4oTt4AaABAg",
        "text": "እኔም አገር ቤት ስገባ ለመስራት እያሰብኩ ነው ሰብስክራይብ አርጉኝ እባካቹ🙏🙏",
        "time": "4 years ago",
        "author": "@kedsttube4484",
        "channel": "UCF4o4U8Y4O3qLyHt6PdC-hA",
        "votes": "0",
        "replies": "2",
        "photo": "https://yt3.ggpht.com/ytc/AIdro_m8T0KlXqoBWM4CXfaOiS9-U2K8cfjB-5gzLYm85MdavNU=s88-c-k-c0x00ffffff-no-rj",
        "heart": false,
        "reply": false,
        "time_parsed": 1623051338.974304
    },
    {
        "cid": "UgyFhC57BQwKXuxhNh14AaABAg",
        "text": "ሰብሰክራየበ አደረገኝ",
        "time": "5 months ago",
        "author": "@MeqdesFanta",
        "channel": "UCerOye7_b_JrRz_e0JDbLCA",
        "votes": "0",
        "replies": "",
        "photo": "https://yt3.ggpht.com/0d9yalnNEQSvXgB9_7v23EY8SEMR8HFYCiPzUNsiG1M6oEQmy0RTCSLCs0FAYSwvcRR9gs39IA=s88-c-k-c0x00ffffff-no-rj",
        "heart": false,
        "reply": false,
        "time_parsed": 1736235338.976295
    },
    {
        "cid": "UgzwjP-aVzvxodoeF994AaABAg",
        "text": "ዩቱዩብ ቻናሌን አስተሚዋውቀልኝ በቅርብ እጀምራለው",
        "time": "4 years ago",
        "author": "@nahomtube9693",
        "channel": "UC6RW7YbOFmticzs_3znpXRw",
        "votes": "0",
        "replies": "2",
        "photo": "https://yt3.ggpht.com/ytc/AIdro_nq_HERY2PIUUZe0KXU7-_lzD59q9p1yITLLJP35SE=s88-c-k-c0x00ffffff-no-rj",
        "heart": true,
        "reply": false,
        "time_parsed": 1623051338.977534
    },
    {
        "cid": "UgxOCx6VTTLCpp0Seht4AaABAg",
        "text": "❤❤❤❤",
        "time": "1 month ago",
        "author": "@TemesgenTemu-z8h",
        "channel": "UCja5SnI8ublX0RsUmOAmqAg",
        "votes": "0",
        "replies": "",
        "photo": "https://yt3.ggpht.com/ytc/AIdro_m8X9mT-HZG5lKIiCAJykIcmXqiL55IlVyGqWptac3ezJgf6r2Can8euNwXp4DTBFAbEw=s88-c-k-c0x00ffffff-no-rj",
        "heart": false,
        "reply": false,
        "time_parsed": 1746603338.979551
    },
    {
        "cid": "UgyW976ePUUhBuVq6Yd4AaABAg.9DY-_gZ_-c49DYZrmKw8mY",
        "text": "አልፍያ Tube እንዛመድ ውዴ እኔ ተዛምቻለሁ",
        "time": "4 years ago (edited)",
        "author": "@ethiolal2148",
        "channel": "UCla7UgebJMbjVXXrtf4MZGA",
        "votes": "1",
        "replies": "",
        "photo": "https://yt3.ggpht.com/S31THPxae3x1FZFfH-WpbgnBcPkSDUGE_B7ujAXaHhlhuZr6u4ALo-jOpksUS0594K_4RAWrLw=s88-c-k-c0x00ffffff-no-rj",
        "heart": false,
        "reply": true,
        "time_parsed": 1623051339.158485
    },
    {
        "cid": "Ugz_fCEUmopW4jEVn1V4AaABAg.9DYHUohH_b19DYJISHsQLs",
        "text": "እንደመርርር",
        "time": "4 years ago",
        "author": "@kedyetube4847",
        "channel": "UCo-jrkxHTIbDOTdJ-FLCc7Q",
        "votes": "0",
        "replies": "",
        "photo": "https://yt3.ggpht.com/ytc/AIdro_kLNnakF45_-YywLRLaAw268sc2M1QrMnF8JUwSmOEXPcs=s88-c-k-c0x00ffffff-no-rj",
        "heart": false,
        "reply": true,
        "time_parsed": 1623051339.325985
    },
    {
        "cid": "Ugx0KF5u5Q7hLP1PcRV4AaABAg.9DYZoQkhPPk9DgwXMQ07OW",
        "text": "እንደማመር",
        "time": "4 years ago",
        "author": "@እሙኢምራንየሀይቅልጅ",
        "channel": "UCTlf5yBzdD62XMVqQrcFsmw",
        "votes": "1",
        "replies": "",
        "photo": "https://yt3.ggpht.com/ytc/AIdro_maWKl72S6vZ7II__kBCWmFK_SpwVdzWtc59TF8NfU=s88-c-k-c0x00ffffff-no-rj",
        "heart": false,
        "reply": true,
        "time_parsed": 1623051339.497953
    },
    {
        "cid": "Ugx0KF5u5Q7hLP1PcRV4AaABAg.9DYZoQkhPPk9Dgwo-tnTaq",
        "text": " @እሙኢምራንየሀይቅልጅ  subscribe አድርገስሃለው",
        "time": "4 years ago",
        "author": "@topnewset",
        "channel": "UCzNHISPPUEg-FAw1xCZsWjg",
        "votes": "0",
        "replies": "",
        "photo": "https://yt3.ggpht.com/5XYGiS7j5envO_0yYRuUWbf6ZEgP7uZp8hmlWjqpkFPMPqMEmHgrCjaf_Qf4psbPuB48OIi4hw=s88-c-k-c0x00ffffff-no-rj",
        "heart": false,
        "reply": true,
        "time_parsed": 1623051339.499323
    },
    {
        "cid": "UgzNmTFM1noh7i_syzV4AaABAg.9DYHjv2w1LX9DYJ3aX9rEx",
        "text": "ሰብሥክራይብ እንደራረግ",
        "time": "4 years ago",
        "author": "@kedyetube4847",
        "channel": "UCo-jrkxHTIbDOTdJ-FLCc7Q",
        "votes": "1",
        "replies": "",
        "photo": "https://yt3.ggpht.com/ytc/AIdro_kLNnakF45_-YywLRLaAw268sc2M1QrMnF8JUwSmOEXPcs=s88-c-k-c0x00ffffff-no-rj",
        "heart": false,
        "reply": true,
        "time_parsed": 1623051339.676328
    },
    {
        "cid": "UgzNmTFM1noh7i_syzV4AaABAg.9DYHjv2w1LX9DYJQqbbg-H",
        "text": " @kedyetube4847  እስሺ አርጊሀለው",
        "time": "4 years ago",
        "author": "@topnewset",
        "channel": "UCzNHISPPUEg-FAw1xCZsWjg",
        "votes": "0",
        "replies": "",
        "photo": "https://yt3.ggpht.com/5XYGiS7j5envO_0yYRuUWbf6ZEgP7uZp8hmlWjqpkFPMPqMEmHgrCjaf_Qf4psbPuB48OIi4hw=s88-c-k-c0x00ffffff-no-rj",
        "heart": false,
        "reply": true,
        "time_parsed": 1623051339.677727
    },
    {
        "cid": "UgzBjuhpUxleX2S4oTt4AaABAg.9DXyJ2AdDn_9DYJJzmkGXZ",
        "text": " tsehaye eshetu  እንደመርሮ",
        "time": "4 years ago",
        "author": "@kedyetube4847",
        "channel": "UCo-jrkxHTIbDOTdJ-FLCc7Q",
        "votes": "0",
        "replies": "",
        "photo": "https://yt3.ggpht.com/ytc/AIdro_kLNnakF45_-YywLRLaAw268sc2M1QrMnF8JUwSmOEXPcs=s88-c-k-c0x00ffffff-no-rj",
        "heart": false,
        "reply": true,
        "time_parsed": 1623051339.872498
    },
    {
        "cid": "UgzBjuhpUxleX2S4oTt4AaABAg.9DXyJ2AdDn_9DYJKdORyrR",
        "text": "እንደመርር",
        "time": "4 years ago",
        "author": "@kedyetube4847",
        "channel": "UCo-jrkxHTIbDOTdJ-FLCc7Q",
        "votes": "0",
        "replies": "",
        "photo": "https://yt3.ggpht.com/ytc/AIdro_kLNnakF45_-YywLRLaAw268sc2M1QrMnF8JUwSmOEXPcs=s88-c-k-c0x00ffffff-no-rj",
        "heart": false,
        "reply": true,
        "time_parsed": 1623051339.873899
    },
    {
        "cid": "UgzwjP-aVzvxodoeF994AaABAg.9DYBEzXdVpE9DYGYQCOE_Q",
        "text": "እኔም ገጨ አርጉኝ",
        "time": "4 years ago",
        "author": "@aminacomedy50",
        "channel": "UCnUclFAW5vupoadAs3l7PmQ",
        "votes": "0",
        "replies": "",
        "photo": "https://yt3.ggpht.com/ytc/AIdro_lDvjpIcLbSDwKhadY13WVTGqHWA9eSQ5RNZv8avka36Ik=s88-c-k-c0x00ffffff-no-rj",
        "heart": false,
        "reply": true,
        "time_parsed": 1623051340.057044
    },
    {
        "cid": "UgzwjP-aVzvxodoeF994AaABAg.9DYBEzXdVpE9DYJMLfbRi-",
        "text": "እንደመርር",
        "time": "4 years ago",
        "author": "@kedyetube4847",
        "channel": "UCo-jrkxHTIbDOTdJ-FLCc7Q",
        "votes": "0",
        "replies": "",
        "photo": "https://yt3.ggpht.com/ytc/AIdro_kLNnakF45_-YywLRLaAw268sc2M1QrMnF8JUwSmOEXPcs=s88-c-k-c0x00ffffff-no-rj",
        "heart": false,
        "reply": true,
        "time_parsed": 1623051340.058571
    }
]